{
  "SDM845": {
    "HLOS": "Msmskunk",
    "Die": [
      "Napali"
    ]
  },
  "SM4125": {
    "HLOS": "Bengal",
    "Die": [
      "Agatti"
      ]
  },
  "SM6115": {
    "HLOS": "Bengal",
    "Die": [
      "Undefined"
      ]
  },
  "SM6125": {
    "HLOS": "Trinket",
    "Die": [
      "Nicobar"
      ]
  },
  "SM6150": {
    "HLOS": "Undefined",
    "Die": [
      "Talos"
      ]
  },
  "SM6150-AC": {
    "HLOS": "Undefined",
    "Die": [
      "Talos"
      ]
  },
  "SM7125": {
    "HLOS": "Atoll",
    "Die": [
      "Rennell"
    ]
  },
  "SM7150": {
    "HLOS": "Sdmmagpie",
    "Die": [
      "Moorea"
    ]
  },
  "SM7150-AB": {
    "HLOS": "Sdmmagpie",
    "Die": [
      "Moorea"
    ]
  },
  "SM7150-AC": {
    "HLOS": "Sdmmagpie",
    "Die": [
      "Moorea"
    ]
  },
  "SM8150": {
    "HLOS": "Msmnile",
    "Die": [
      "Hana"
    ]
  },
  "SM8150-AC": {
    "HLOS": "Msmnile",
    "Die": [
      "Hana"
    ]
  },
  "SM4250-AA": {
    "HLOS": "Bengal",
    "Die": [
      "Kamorta"
    ]
  },
  "SM6225": {
    "HLOS": "Bengal",
    "Die": [
      "Bitra",
      "Divar"
    ]
  },
  "SM6225-AD": {
    "HLOS": "Bengal",
    "Die": [
      "Bitra",
      "Divar"
    ]
  },
  "SM6250": {
    "HLOS": "Atoll",
    "Die": [
      "Atoll"
    ]
  },
  "SM7225": {
    "HLOS": "Lito",
    "Die": [
      "Bitra",
      "Lagoon"
    ]
  },
  "SM7225-2-AB": {
    "HLOS": "Lito",
    "Die": [
      "Bitra",
      "Lagoon"
    ]
  },
  "SM7250": {
    "HLOS": "Lito",
    "Die": [
      "Saipan",
      "Nairo"
    ]
  },
  "SM7250-AA": {
    "HLOS": "Lito",
    "Die": [
      "Saipan",
      "Nairo"
    ]
  },
  "SM7250-AB": {
    "HLOS": "Lito",
    "Die": [
      "Saipan",
      "Nairo"
    ]
  },
  "SM7250-AC": {
    "HLOS": "Lito",
    "Die": [
      "Saipan",
      "Nairo"
    ]
  },
  "SM8250": {
    "HLOS": "Kona",
    "Die": [
      "Kona"
    ]
  },
  "SM8250-AB": {
    "HLOS": "Kona",
    "Die": [
      "Kona"
    ]
  },
  "SM8250-AC": {
    "HLOS": "Kona",
    "Die": [
      "Kona"
    ]
  },
  "SM4350": {
    "HLOS": "Holi",
    "Die": [
      "Mannar"
    ]
  },
  "SM4350-AC": {
    "HLOS": "Holi",
    "Die": [
      "Mannar"
    ]
  },
  "SM4375": {
    "HLOS": "Holi",
    "Die": [
      "Conic",
      "Blair_Lite"
    ]
  },
  "SM6350": {
    "HLOS": "Lito",
    "Die": [
      "Bitra"
    ]
  },
  "SM6370": {
    "HLOS": "Holi",
    "Die": [
      "Aran"
    ]
  },
  "SM6375": {
    "HLOS": "Holi",
    "Die": [
      "Blair",
      "Strait"
    ]
  },
  "SM6375-AB": {
    "HLOS": "Holi",
    "Die": [
      "Blair",
      "Strait"
    ]
  },
  "SM6375-AC": {
    "HLOS": "Holi",
    "Die": [
      "Blair",
      "Strait"
    ]
  },
  "SM7315": {
    "HLOS": "Lahaina",
    "Die": [
      "Faroe"
    ]
  },
  "SM7325": {
    "HLOS": "Lahaina",
    "Die": [
      "Kodiak",
      "Yupik"
    ]
  },
  "SM7325-AE": {
    "HLOS": "Lahaina",
    "Die": [
      "Kodiak",
      "Yupik"
    ]
  },
  "SM7325-AF": {
    "HLOS": "Lahaina",
    "Die": [
      "Kodiak",
      "Yupik"
    ]
  },
  "SM7350": {
    "HLOS": "Lahaina",
    "Die": [
      "Cedros"
    ]
  },
  "SM8325": {
    "HLOS": "Lahaina",
    "Die": [
      "Bodrum"
    ]
  },
  "SM8350": {
    "HLOS": "Lahaina",
    "Die": [
      "Lahaina"
    ]
  },
  "SM8350-AC": {
    "HLOS": "Lahaina",
    "Die": [
      "Lahaina"
    ]
  },
  "SM4425": {
    "HLOS": "Waipio",
    "Die": [
      "Puna"
    ]
  },
  "SM4450": {
    "HLOS": "Parrot",
    "Die": [
      "Clarence"
    ]
  },
  "SM6450": {
    "HLOS": "Parrot",
    "Die": [
      "Netrani",
      "Parrot"
    ]
  },
  "SM6450-AC": {
    "HLOS": "Parrot",
    "Die": [
      "Netrani",
      "Parrot"
    ]
  },
  "SM6475": {
    "HLOS": "Parrot",
    "Die": [
      "Netrani",
      "Parrot"
    ]
  },
  "SM6475-AB": {
    "HLOS": "Parrot",
    "Die": [
      "Netrani",
      "Parrot"
    ]
  },
  "SM7435": {
    "HLOS": "Parrot",
    "Die": [
      "Netrani",
      "Parrot"
    ]
  },
  "SM7435-AB": {
    "HLOS": "Parrot",
    "Die": [
      "Netrani",
      "Parrot"
    ]
  },
  "SM7450": {
    "HLOS": "Waipio",
    "Die": [
      "Fillmore",
      "Diwali"
    ]
  },
  "SM7450-AB": {
    "HLOS": "Waipio",
    "Die": [
      "Fillmore",
      "Diwali"
    ]
  },
  "SM7475": {
    "HLOS": "Waipio",
    "Die": [
      "Tofino"
    ]
  },
  "SM7475-AC": {
    "HLOS": "Waipio",
    "Die": [
      "Tofino"
    ]
  },
  "SM8415": {
    "HLOS": "Waipio",
    "Die": [
      "Alakai"
    ]
  },
  "SM8450": {
    "HLOS": "Waipio",
    "Die": [
      "Taro"
    ]
  },
  "SM8475": {
    "HLOS": "Waipio",
    "Die": [
      "Cape",
      "Palima"
    ]
  },
  "SM7525": {
    "HLOS": "Kalama",
    "Die": [
      "Shaw"
    ]
  },
  "SM7550": {
    "HLOS": "Kalama",
    "Die": [
      "Crow",
      "Kapiti"
    ]
  },
  "SM7550-AB": {
    "HLOS": "Kalama",
    "Die": [
      "Crow",
      "Kapiti"
    ]
  },
  "QCS8550": {
    "HLOS": "KalamaP",
    "Die": [
      "Kailua"
    ]
  },
  "SM8550": {
    "HLOS": "Kalama",
    "Die": [
      "Kailua"
    ]
  },
  "SM8550-AB": {
    "HLOS": "Kalama",
    "Die": [
      "Kailua"
    ]
  },
  "SM8550-AC": {
    "HLOS": "Kalama",
    "Die": [
      "Kailua"
    ]
  },
  "SM4635": {
    "HLOS": "Pitti",
    "Die": [
      "Kalpeni"
    ]
  },
  "SM7635": {
    "HLOS":"Volcano",
    "Die": [
      "Milos"
    ]
  },
  "SM8635": {
    "HLOS":"Undefined",
    "Die": [
      "Palawan"
    ]
  },
  "SM8650": {
    "HLOS":"Pineapple",
    "Die": [
      "Lanai"
    ]
  },
  "SM8650-AB": {
    "HLOS":"Pineapple",
    "Die": [
      "Lanai"
    ]
  },
  "SM8650-AC": {
    "HLOS":"Pineapple",
    "Die": [
      "Lanai"
    ]
  },
  "SM7750": {
    "HLOS":"Kera",
    "Die": [
      "Eliza"
    ]
  },
  "SM7750-AC": {
    "HLOS":"Kera",
    "Die": [
      "Eliza"
    ]
  },
  "SM8735": {
    "HLOS":"Undefined",
    "Die": [
      "Bonito"
    ]
  },
  "CQ8750S": {
    "HLOS": "SunP",
    "Die": [
      "Pakala"
    ]
  },
  "SM8750": {
    "HLOS": "Sun",
    "Die": [
      "Pakala"
    ]
  },
  "SM8750-AB": {
    "HLOS": "Sun",
    "Die": [
      "Pakala"
    ]
  },
  "SM8750-AC": {
    "HLOS": "Sun",
    "Die": [
      "Pakala"
    ]
  },
  "SM8750-3-AB": {
    "HLOS": "Sun",
    "Die": [
      "Pakala"
    ]
  },
  "SM8850": {
    "HLOS": "Kanoe",
    "Die": [
      "Kaanapali"
    ]
  },
  "SM8850-AC": {
    "HLOS": "Kanoe",
    "Die": [
      "Kaanapali"
    ]
  }
}